df_config/__init__.py
df_config/__main__.py
df_config/application.py
df_config/checks.py
df_config/context_processors.py
df_config/iniconf.py
df_config/manage.py
df_config/models.py
df_config/root_urls.py
df_config/urls.py
df_config/utils.py
df_config/apps/__init__.py
df_config/apps/allauth.py
df_config/apps/backends.py
df_config/apps/middleware.py
df_config/apps/pipeline.py
df_config/config/__init__.py
df_config/config/base.py
df_config/config/defaults.py
df_config/config/dynamic_settings.py
df_config/config/fields.py
df_config/config/fields_providers.py
df_config/config/merger.py
df_config/config/url.py
df_config/config/values_providers.py
df_config/extra/__init__.py
df_config/extra/loki.py
df_config/guesses/__init__.py
df_config/guesses/apps.py
df_config/guesses/auth.py
df_config/guesses/databases.py
df_config/guesses/djt.py
df_config/guesses/log.py
df_config/guesses/misc.py
df_config/guesses/pipeline.py
df_config/guesses/social_providers.py
df_config/guesses/staticfiles.py
df_config/management/__init__.py
df_config/management/commands/__init__.py
df_config/management/commands/collectstatic.py
df_config/management/commands/config.py
df_config/management/commands/server.py
df_config/static/favicon/apple-touch-icon-precomposed.png
df_config/static/favicon/apple-touch-icon.png
df_config/static/favicon/favicon.ico
df_config/static/favicon/robots.txt
df_config/static/js/df_config.min.js
df_config/static/js/df_config.min.js.map
npm/df_config/app.ts
df_config-1.2.83.dist-info/METADATA
df_config-1.2.83.dist-info/WHEEL
df_config-1.2.83.dist-info/licenses/LICENSE
df_config-1.2.83.dist-info/RECORD
